google_drive_export.py
google_drive_export-0.1.3.dist-info/licenses/LICENSE
google_drive_export-0.1.3.dist-info/METADATA
google_drive_export-0.1.3.dist-info/WHEEL
google_drive_export-0.1.3.dist-info/entry_points.txt
google_drive_export-0.1.3.dist-info/top_level.txt
google_drive_export-0.1.3.dist-info/RECORD
