Metadata-Version: 2.4
Name: google-drive-export
Version: 0.1.3
Summary: Export your Google Drive data
Author: Corey Goldberg
Maintainer: Corey Goldberg
License-Expression: MIT
Project-URL: homepage, https://github.com/cgoldberg/google-drive-export
Project-URL: source, https://github.com/cgoldberg/google-drive-export
Project-URL: download, https://pypi.org/project/google-drive-export
Keywords: google,drive,google-drive,backup,export,takeout
Classifier: Environment :: Console
Classifier: Programming Language :: Python
Classifier: Programming Language :: Python :: 3
Classifier: Programming Language :: Python :: 3.10
Classifier: Programming Language :: Python :: 3.11
Classifier: Programming Language :: Python :: 3.12
Classifier: Programming Language :: Python :: 3.13
Classifier: Programming Language :: Python :: 3.14
Requires-Python: >=3.9
License-File: LICENSE
Requires-Dist: google-api-python-client==2.185.0
Requires-Dist: google-auth-httplib2==0.2.0
Requires-Dist: google-auth-oauthlib==1.2.2
Dynamic: license-file
